main.py
core/__init__.py
core/banner_grabber.py
core/port_scanner.py
core/stealth_scanner.py
core/vulnerability_checker.py
output/__init__.py
output/reporters.py
simple_network_scanner-1.0.5.dist-info/licenses/LICENSE
utils/__init__.py
utils/config.py
simple_network_scanner-1.0.5.dist-info/METADATA
simple_network_scanner-1.0.5.dist-info/WHEEL
simple_network_scanner-1.0.5.dist-info/entry_points.txt
simple_network_scanner-1.0.5.dist-info/top_level.txt
simple_network_scanner-1.0.5.dist-info/RECORD
