Metadata-Version: 2.4
Name: simple-network-scanner
Version: 1.0.5
Summary: A comprehensive network port scanner with vulnerability detection
Home-page: https://github.com/Zeusfail/Simple-Network-Scanner
Author: Dylan Gallemard
Author-email: dylangallemard@gmail.com
Classifier: Programming Language :: Python :: 3
Classifier: License :: OSI Approved :: GNU General Public License v3 (GPLv3)
Classifier: Operating System :: OS Independent
Requires-Python: >=3.6
License-File: LICENSE
Requires-Dist: scapy>=2.4.0
Requires-Dist: rich>=12.0.0
Dynamic: author
Dynamic: author-email
Dynamic: classifier
Dynamic: description
Dynamic: description-content-type
Dynamic: home-page
Dynamic: license-file
Dynamic: requires-dist
Dynamic: requires-python
Dynamic: summary
